{
  "Version": 3,
  "Meta": {
    "Duration": 3.567,
    "Fps": 30.0,
    "Loop": true,
    "AreBeziersRestricted": true,
    "FadeInTime": 1.0,
    "FadeOutTime": 1.0,
    "CurveCount": 43,
    "TotalSegmentCount": 89,
    "TotalPointCount": 101,
    "UserDataCount": 0,
    "TotalUserDataSize": 0
  },
  "Curves": [
    {
      "Target": "Parameter",
      "Id": "PARAM_ANGLE_X",
      "FadeInTime": -1.0,
      "FadeOutTime": -1.0,
      "Segments": [
        0,
        0,
        0,
        3.167,
        0,
        0,
        3.567,
        0
      ]
    },
    {
      "Target": "Parameter",
      "Id": "PARAM_ANGLE_Y",
      "FadeInTime": -1.0,
      "FadeOutTime": -1.0,
      "Segments": [
        0,
        0,
        0,
        0.233,
        -4.561,
        0,
        0.7,
        10.463,
        0,
        1.267,
        -30,
        0,
        1.633,
        -4.561,
        0,
        1.967,
        -30,
        1,
        2.078,
        -30,
        2.189,
        -20.469,
        2.3,
        -8.424,
        1,
        2.378,
        0.007,
        2.455,
        1.931,
        2.533,
        1.931,
        0,
        2.833,
        -2.369,
        0,
        3.167,
        0,
        0,
        3.567,
        0
      ]
    },
    {
      "Target": "Parameter",
      "Id": "PARAM_ANGLE_Z",
      "FadeInTime": -1.0,
      "FadeOutTime": -1.0,
      "Segments": [
        0,
        0,
        0,
        2.9,
        0,
        0,
        3.167,
        0,
        0,
        3.567,
        0
      ]
    },
    {
      "Target": "Parameter",
      "Id": "PARAM_EYE_L_OPEN",
      "FadeInTime": -1.0,
      "FadeOutTime": -1.0,
      "Segments": [
        0,
        1,
        0,
        1,
        1,
        0,
        1.3,
        0,
        0,
        1.6,
        1,
        0,
        3.567,
        1
      ]
    },
    {
      "Target": "Parameter",
      "Id": "PARAM_EYE_L_SMILE",
      "FadeInTime": -1.0,
      "FadeOutTime": -1.0,
      "Segments": [
        0,
        0,
        0,
        3.567,
        0
      ]
    },
    {
      "Target": "Parameter",
      "Id": "PARAM_EYE_R_OPEN",
      "FadeInTime": -1.0,
      "FadeOutTime": -1.0,
      "Segments": [
        0,
        1,
        0,
        1,
        1,
        0,
        1.3,
        0,
        0,
        1.6,
        1,
        0,
        3.567,
        1
      ]
    },
    {
      "Target": "Parameter",
      "Id": "PARAM_EYE_R_SMILE",
      "FadeInTime": -1.0,
      "FadeOutTime": -1.0,
      "Segments": [
        0,
        0,
        0,
        3.567,
        0
      ]
    },
    {
      "Target": "Parameter",
      "Id": "PARAM_EYE_BALL_X",
      "FadeInTime": -1.0,
      "FadeOutTime": -1.0,
      "Segments": [
        0,
        0,
        0,
        3.567,
        0
      ]
    },
    {
      "Target": "Parameter",
      "Id": "PARAM_EYE_BALL_Y",
      "FadeInTime": -1.0,
      "FadeOutTime": -1.0,
      "Segments": [
        0,
        0,
        0,
        3.567,
        0
      ]
    },
    {
      "Target": "Parameter",
      "Id": "PARAM_YANQIU",
      "FadeInTime": -1.0,
      "FadeOutTime": -1.0,
      "Segments": [
        0,
        0,
        0,
        3.567,
        0
      ]
    },
    {
      "Target": "Parameter",
      "Id": "PARAM_YANQIU_2",
      "FadeInTime": -1.0,
      "FadeOutTime": -1.0,
      "Segments": [
        0,
        0,
        0,
        3.567,
        0
      ]
    },
    {
      "Target": "Parameter",
      "Id": "PARAM_BROW_L_Y",
      "FadeInTime": -1.0,
      "FadeOutTime": -1.0,
      "Segments": [
        0,
        0,
        0,
        3.567,
        0
      ]
    },
    {
      "Target": "Parameter",
      "Id": "PARAM_BROW_R_Y",
      "FadeInTime": -1.0,
      "FadeOutTime": -1.0,
      "Segments": [
        0,
        0,
        0,
        3.567,
        0
      ]
    },
    {
      "Target": "Parameter",
      "Id": "PARAM_BROW_L_X",
      "FadeInTime": -1.0,
      "FadeOutTime": -1.0,
      "Segments": [
        0,
        0,
        0,
        3.567,
        0
      ]
    },
    {
      "Target": "Parameter",
      "Id": "PARAM_BROW_R_X",
      "FadeInTime": -1.0,
      "FadeOutTime": -1.0,
      "Segments": [
        0,
        0,
        0,
        3.567,
        0
      ]
    },
    {
      "Target": "Parameter",
      "Id": "PARAM_BROW_L_ANGLE",
      "FadeInTime": -1.0,
      "FadeOutTime": -1.0,
      "Segments": [
        0,
        0,
        0,
        3.567,
        0
      ]
    },
    {
      "Target": "Parameter",
      "Id": "PARAM_BROW_R_ANGLE",
      "FadeInTime": -1.0,
      "FadeOutTime": -1.0,
      "Segments": [
        0,
        0,
        0,
        3.567,
        0
      ]
    },
    {
      "Target": "Parameter",
      "Id": "PARAM_BROW_L_FORM",
      "FadeInTime": -1.0,
      "FadeOutTime": -1.0,
      "Segments": [
        0,
        0,
        0,
        3.567,
        0
      ]
    },
    {
      "Target": "Parameter",
      "Id": "PARAM_BROW_R_FORM",
      "FadeInTime": -1.0,
      "FadeOutTime": -1.0,
      "Segments": [
        0,
        0,
        0,
        3.567,
        0
      ]
    },
    {
      "Target": "Parameter",
      "Id": "PARAM_MOUTH_FORM",
      "FadeInTime": -1.0,
      "FadeOutTime": -1.0,
      "Segments": [
        0,
        0,
        0,
        3.567,
        0
      ]
    },
    {
      "Target": "Parameter",
      "Id": "PARAM_MOUTH_OPEN_Y",
      "FadeInTime": -1.0,
      "FadeOutTime": -1.0,
      "Segments": [
        0,
        0,
        0,
        3.567,
        0
      ]
    },
    {
      "Target": "Parameter",
      "Id": "PARAM_CHEEK",
      "FadeInTime": -1.0,
      "FadeOutTime": -1.0,
      "Segments": [
        0,
        0,
        0,
        3.567,
        0
      ]
    },
    {
      "Target": "Parameter",
      "Id": "PARAM_CHEEK_2",
      "FadeInTime": -1.0,
      "FadeOutTime": -1.0,
      "Segments": [
        0,
        0,
        0,
        3.567,
        0
      ]
    },
    {
      "Target": "Parameter",
      "Id": "PARAM_LIUHAN_2",
      "FadeInTime": -1.0,
      "FadeOutTime": -1.0,
      "Segments": [
        0,
        0,
        0,
        3.567,
        0
      ]
    },
    {
      "Target": "Parameter",
      "Id": "PARAM_BODY_ANGLE_X",
      "FadeInTime": -1.0,
      "FadeOutTime": -1.0,
      "Segments": [
        0,
        0,
        0,
        2.9,
        0,
        0,
        3.167,
        0,
        0,
        3.567,
        0
      ]
    },
    {
      "Target": "Parameter",
      "Id": "PARAM_BODY_ANGLE_Y",
      "FadeInTime": -1.0,
      "FadeOutTime": -1.0,
      "Segments": [
        0,
        0,
        0,
        0.067,
        0,
        0,
        0.2,
        -0.254,
        1,
        0.256,
        -0.254,
        0.311,
        -0.104,
        0.367,
        0.274,
        1,
        0.434,
        0.728,
        0.5,
        1,
        0.567,
        1,
        1,
        0.634,
        1,
        0.7,
        0.774,
        0.767,
        0.274,
        1,
        0.878,
        -0.559,
        0.989,
        -1,
        1.1,
        -1,
        0,
        1.7,
        -1,
        0,
        1.933,
        -1,
        0,
        2.5,
        0.519,
        0,
        3,
        0,
        0,
        3.167,
        0,
        0,
        3.567,
        0
      ]
    },
    {
      "Target": "Parameter",
      "Id": "PARAM_BODY_ANGLE_Z",
      "FadeInTime": -1.0,
      "FadeOutTime": -1.0,
      "Segments": [
        0,
        0,
        0,
        2.9,
        0,
        0,
        3.167,
        0,
        0,
        3.567,
        0
      ]
    },
    {
      "Target": "Parameter",
      "Id": "PARAM_UPBACK",
      "FadeInTime": -1.0,
      "FadeOutTime": -1.0,
      "Segments": [
        0,
        0,
        0,
        3.567,
        0
      ]
    },
    {
      "Target": "Parameter",
      "Id": "PARAM_BREATH",
      "FadeInTime": -1.0,
      "FadeOutTime": -1.0,
      "Segments": [
        0,
        0,
        0,
        2.9,
        0,
        0,
        3.167,
        0,
        0,
        3.567,
        0
      ]
    },
    {
      "Target": "Parameter",
      "Id": "PARAM_KATA_L",
      "FadeInTime": -1.0,
      "FadeOutTime": -1.0,
      "Segments": [
        0,
        0,
        0,
        3.567,
        0
      ]
    },
    {
      "Target": "Parameter",
      "Id": "PARAM_KATA_R",
      "FadeInTime": -1.0,
      "FadeOutTime": -1.0,
      "Segments": [
        0,
        0,
        0,
        3.567,
        0
      ]
    },
    {
      "Target": "Parameter",
      "Id": "PARAM_SIKAO",
      "FadeInTime": -1.0,
      "FadeOutTime": -1.0,
      "Segments": [
        0,
        0,
        0,
        3.567,
        0
      ]
    },
    {
      "Target": "Parameter",
      "Id": "PARAM_MOQUAN",
      "FadeInTime": -1.0,
      "FadeOutTime": -1.0,
      "Segments": [
        0,
        0,
        0,
        3.567,
        0
      ]
    },
    {
      "Target": "Parameter",
      "Id": "PARAM_DAIJING",
      "FadeInTime": -1.0,
      "FadeOutTime": -1.0,
      "Segments": [
        0,
        0,
        0,
        3.567,
        0
      ]
    },
    {
      "Target": "Parameter",
      "Id": "PARAM_CHEYIDAI",
      "FadeInTime": -1.0,
      "FadeOutTime": -1.0,
      "Segments": [
        0,
        0,
        0,
        3.567,
        0
      ]
    },
    {
      "Target": "Parameter",
      "Id": "PARAM_ARM_L",
      "FadeInTime": -1.0,
      "FadeOutTime": -1.0,
      "Segments": [
        0,
        0,
        0,
        0.833,
        0.1,
        0,
        1.833,
        -0.2,
        0,
        2.833,
        -0.2,
        0,
        3.567,
        0
      ]
    },
    {
      "Target": "Parameter",
      "Id": "PARAM_ARM_L2",
      "FadeInTime": -1.0,
      "FadeOutTime": -1.0,
      "Segments": [
        0,
        0,
        0,
        3.567,
        0
      ]
    },
    {
      "Target": "Parameter",
      "Id": "PARAM_ARM_L3",
      "FadeInTime": -1.0,
      "FadeOutTime": -1.0,
      "Segments": [
        0,
        0,
        0,
        1,
        0.2,
        0,
        2,
        -0.3,
        0,
        3,
        -0.3,
        0,
        3.567,
        0
      ]
    },
    {
      "Target": "Parameter",
      "Id": "PARAM_ARM_R",
      "FadeInTime": -1.0,
      "FadeOutTime": -1.0,
      "Segments": [
        0,
        0,
        0,
        3.567,
        0
      ]
    },
    {
      "Target": "Parameter",
      "Id": "PARAM_ARM_R2",
      "FadeInTime": -1.0,
      "FadeOutTime": -1.0,
      "Segments": [
        0,
        0,
        0,
        3.567,
        0
      ]
    },
    {
      "Target": "Parameter",
      "Id": "PARAM_ARM_R3",
      "FadeInTime": -1.0,
      "FadeOutTime": -1.0,
      "Segments": [
        0,
        0,
        0,
        0.833,
        -0.3,
        0,
        1.833,
        0.5,
        0,
        2.833,
        0.5,
        0,
        3.567,
        0
      ]
    },
    {
      "Target": "Parameter",
      "Id": "PARAM_HUMUJING",
      "FadeInTime": -1.0,
      "FadeOutTime": -1.0,
      "Segments": [
        0,
        0,
        0,
        1.833,
        0.8,
        0,
        3.567,
        0
      ]
    },
    {
      "Target": "Parameter",
      "Id": "PARAM_YIDAI",
      "FadeInTime": -1.0,
      "FadeOutTime": -1.0,
      "Segments": [
        0,
        0,
        0,
        3.567,
        0
      ]
    }
  ],
  "UserData": []
}